[1,["177b0b2d9@6c48a"],["_textureSource"],["cc.SpriteFrame","cc.SpriteAtlas"],0,[[[{"name":"bg_wulong_daojuxuanze_honglong","rect":{"x":203,"y":753,"width":177,"height":203},"offset":{"x":0,"y":0},"originalSize":{"width":177,"height":203},"rotated":false,"capInsets":[0,0,0,0],"packable":true,"pixelsToUnit":100,"pivot":{"x":0.5,"y":0.5},"meshType":0}],[0],0,[0],[0],[0]],[[{"name":"icon_dt_loading_0","rect":{"x":895,"y":212,"width":796,"height":48},"offset":{"x":0,"y":0},"originalSize":{"width":796,"height":48},"rotated":true,"capInsets":[22,12,24,16],"packable":true,"pixelsToUnit":100,"pivot":{"x":0.5,"y":0.5},"meshType":0}],[0],0,[0],[0],[0]],[[{"name":"bg_dengji_jindutiao","rect":{"x":949,"y":690,"width":172,"height":46},"offset":{"x":0,"y":0},"originalSize":{"width":172,"height":46},"rotated":true,"capInsets":[20,11,23,11],"packable":true,"pixelsToUnit":100,"pivot":{"x":0.5,"y":0.5},"meshType":0}],[0],0,[0],[0],[0]],[[{"name":"bg_wulong_jiesuandikuang-youwin","rect":{"x":949,"y":868,"width":146,"height":39},"offset":{"x":0,"y":0},"originalSize":{"width":146,"height":39},"rotated":true,"capInsets":[0,0,0,0],"packable":true,"pixelsToUnit":100,"pivot":{"x":0.5,"y":0.5},"meshType":0}],[0],0,[0],[0],[0]],[[{"name":"bg_wulong_daojuxuanze_contani","rect":{"x":3,"y":980,"width":182,"height":41},"offset":{"x":0,"y":0},"originalSize":{"width":182,"height":41},"rotated":false,"capInsets":[0,0,0,0],"packable":true,"pixelsToUnit":100,"pivot":{"x":0.5,"y":0.5},"meshType":0}],[0],0,[0],[0],[0]],[[{"name":"btn_caozuo_max_di","rect":{"x":758,"y":753,"width":100,"height":87},"offset":{"x":0,"y":0},"originalSize":{"width":100,"height":87},"rotated":false,"capInsets":[0,0,0,0],"packable":true,"pixelsToUnit":100,"pivot":{"x":0.5,"y":0.5},"meshType":0}],[0],0,[0],[0],[0]],[[{"name":"bg_touxiangbox_1","rect":{"x":903,"y":3,"width":103,"height":112},"offset":{"x":0,"y":0},"originalSize":{"width":103,"height":112},"rotated":true,"capInsets":[0,0,0,0],"packable":true,"pixelsToUnit":100,"pivot":{"x":0.5,"y":0.5},"meshType":0}],[0],0,[0],[0],[0]],[[{"name":"bg_touxiangbox_2","rect":{"x":895,"y":112,"width":94,"height":111},"offset":{"x":0,"y":0},"originalSize":{"width":94,"height":111},"rotated":true,"capInsets":[0,0,0,0],"packable":true,"pixelsToUnit":100,"pivot":{"x":0.5,"y":0.5},"meshType":0}],[0],0,[0],[0],[0]],[[{"name":"bg_wulong_minor","rect":{"x":949,"y":212,"width":71,"height":25},"offset":{"x":0,"y":0},"originalSize":{"width":71,"height":25},"rotated":false,"capInsets":[0,0,0,0],"packable":true,"pixelsToUnit":100,"pivot":{"x":0.5,"y":0.5},"meshType":0}],[0],0,[0],[0],[0]],[[{"name":"bg_wulong_jiesuandikuang-minijackpor","rect":{"x":949,"y":243,"width":410,"height":69},"offset":{"x":0,"y":0},"originalSize":{"width":410,"height":69},"rotated":true,"capInsets":[0,0,0,0],"packable":true,"pixelsToUnit":100,"pivot":{"x":0.5,"y":0.5},"meshType":0}],[0],0,[0],[0],[0]],[[{"name":"bg_wulong_xiaoyouxi_jiesuandikuang","rect":{"x":3,"y":59,"width":886,"height":688},"offset":{"x":0,"y":0},"originalSize":{"width":886,"height":688},"rotated":false,"capInsets":[0,0,0,0],"packable":true,"pixelsToUnit":100,"pivot":{"x":0.5,"y":0.5},"meshType":0}],[0],0,[0],[0],[0]],[[{"name":"bg_wulong_mini","rect":{"x":949,"y":659,"width":50,"height":25},"offset":{"x":0,"y":0},"originalSize":{"width":50,"height":25},"rotated":false,"capInsets":[0,0,0,0],"packable":true,"pixelsToUnit":100,"pivot":{"x":0.5,"y":0.5},"meshType":0}],[0],0,[0],[0],[0]],[[{"name":"bg_wulong_daojuxuanze_lanlong","rect":{"x":386,"y":753,"width":180,"height":200},"offset":{"x":0,"y":0},"originalSize":{"width":180,"height":200},"rotated":false,"capInsets":[0,0,0,0],"packable":true,"pixelsToUnit":100,"pivot":{"x":0.5,"y":0.5},"meshType":0}],[0],0,[0],[0],[0]],[[{"name":"bg_wulong_daojuxuanze_zilong","rect":{"x":572,"y":753,"width":180,"height":200},"offset":{"x":0,"y":0},"originalSize":{"width":180,"height":200},"rotated":false,"capInsets":[0,0,0,0],"packable":true,"pixelsToUnit":100,"pivot":{"x":0.5,"y":0.5},"meshType":0}],[0],0,[0],[0],[0]],[[{"name":"auto-fivedragon","spriteFrames":["bg_wulong_daojuxuanze_biaoti","c8PciIk3JMdZ/5Tp3KZoGN@f9941","bg_touxiangbox_1","38DO2fBWhFgLLyUL8VqeDS@f9941","bg_wulong_xiaoyouxi_jiesuandikuang","75km+vMhZLkYfS4bqOpKk3@f9941","default_sprite_splash","b3YUeVKqdEwoRCiDNjy/c0@f9941","bg_touxiangbox_2","3ebiRYwFJAcqvUe3NaKguv@f9941","icon_dt_loading_0","13EB9XXLNOv5uG5XD6CU+F@f9941","bg_wulong_minor","421gyNZBFMvorO8Vuc5UX2@f9941","bg_wulong_jiesuandikuang-minijackpor","66TusTthlLqIwpSUButvIO@f9941","bg_wulong_mini","783+g7RclKq52TNmG4Z8Eq@f9941","bg_dengji_jindutiao","25VSkeMG1HoIBotIlQ1LRA@f9941","bg_wulong_jiesuandikuang-youwin","26Pc6N65VBJ5iCbWMEcyoU@f9941","bg_wulong_grand","b6LBxXmglLF46x1BSfGVce@f9941","bg_wulong_xiaoyouxi_zilong","e4jUvZs6BBA4vjGajqgDjd@f9941","bg_wulong_daojuxuanze_contani","29yTJL1CxCsb5OOx8eVcjB@f9941","bg_wulong_major","f7FnNfjB5LRLDVMiPOpMiz@f9941","bg_wulong_daojuxuanze_honglong","127JNbduhHrIj1P7QeYtkT@f9941","bg_wulong_daojuxuanze_lanlong","8fChjsQDlJibRJTG3QCxfW@f9941","bg_wulong_daojuxuanze_zilong","93ozA5QhFGyJ2T4F3a9xIj@f9941","btn_caozuo_max_di","2d0b1wexVHGYWlSszgoTMd@f9941","mianfei","f2UsRpS9ZE3bUa0tQljW1g@f9941","icon_dt_loading_1","76SgParXxMooRUDxP0gjw9@f9941","bg_wulong_jiesuandikuang-biaoti","31Y/1ipqNHjJRJz+EB5wAz@f9941","kuang","68fY12TAVL0q/hsV2eUgkF@f9941","zhongjian","c7YIb0A9xL/KcCzT5g65RY@f9941","bg_wulong_daojuxuanze_lvlong","7d1QNWJs5F74Xm5wgistcu@f9941","bg_wulong_daojuxuanze_huilong","fegqXhqlFFOatxI3PkmqgO@f9941"]}],[1],0,[],[],[]],[[{"name":"default_sprite_splash","rect":{"x":895,"y":59,"width":2,"height":2},"offset":{"x":0,"y":0},"originalSize":{"width":2,"height":2},"rotated":false,"capInsets":[0,0,0,0],"packable":true,"pixelsToUnit":100,"pivot":{"x":0.5,"y":0.5},"meshType":0}],[0],0,[0],[0],[0]],[[{"name":"bg_wulong_grand","rect":{"x":994,"y":868,"width":75,"height":27},"offset":{"x":0,"y":0},"originalSize":{"width":75,"height":27},"rotated":true,"capInsets":[0,0,0,0],"packable":true,"pixelsToUnit":100,"pivot":{"x":0.5,"y":0.5},"meshType":0}],[0],0,[0],[0],[0]],[[{"name":"bg_wulong_daojuxuanze_biaoti","rect":{"x":3,"y":3,"width":894,"height":50},"offset":{"x":0,"y":0},"originalSize":{"width":894,"height":50},"rotated":false,"capInsets":[0,0,0,0],"packable":true,"pixelsToUnit":100,"pivot":{"x":0.5,"y":0.5},"meshType":0}],[0],0,[0],[0],[0]],[[{"name":"bg_wulong_xiaoyouxi_zilong","rect":{"x":3,"y":753,"width":194,"height":221},"offset":{"x":0,"y":0},"originalSize":{"width":194,"height":221},"rotated":false,"capInsets":[0,0,0,0],"packable":true,"pixelsToUnit":100,"pivot":{"x":0.5,"y":0.5},"meshType":0}],[0],0,[0],[0],[0]],[[{"name":"mianfei","rect":{"x":758,"y":846,"width":172,"height":78},"offset":{"x":0.5,"y":-0.5},"originalSize":{"width":179,"height":85},"rotated":true,"capInsets":[0,0,0,0],"packable":true,"pixelsToUnit":100,"pivot":{"x":0.5,"y":0.5},"meshType":0}],[0],0,[0],[0],[0]],[[{"name":"bg_wulong_major","rect":{"x":191,"y":980,"width":77,"height":26},"offset":{"x":0,"y":0},"originalSize":{"width":77,"height":26},"rotated":false,"capInsets":[0,0,0,0],"packable":true,"pixelsToUnit":100,"pivot":{"x":0.5,"y":0.5},"meshType":0}],[0],0,[0],[0],[0]]]]
