[1,["7dOA9TgddLq5CbWEqxZJkG@6c48a","1a5iUPzehCbbdPqnit04vS"],["node","root","data","_skeletonData"],[["cc.Node",["_name","_components","_prefab","_children","_parent","_lpos"],2,9,4,2,1,5],["cc.UITransform",["node","__prefab","_contentSize"],3,1,4,5],["sp.SkeletonData",["_name","_atlasText","textureNames","_skeletonJson","textures"],-1,3],["cc.Prefab",["_name"],2],["cc.CompPrefabInfo",["fileId"],2],["cc.PrefabInfo",["fileId","instance","targetOverrides","nestedPrefabInstanceRoots","root","asset"],-1,1,1],["sp.Skeleton",["defaultSkin","defaultAnimation","_premultipliedAlpha","_preCacheMode","node","__prefab","_skeletonData"],-1,1,4,6]],[[4,0,2],[5,0,1,2,3,4,5,5],[2,0,1,2,3,4,5],[3,0,2],[0,0,3,1,2,2],[0,0,4,1,2,5,2],[1,0,1,1],[1,0,1,2,1],[6,0,1,2,3,4,5,6,5]],[[[[2,"qiuqiu_fapaiguan","\r\nqiuqiu_fapaiguan.png\r\nsize: 512,128\r\nformat: RGBA8888\r\nfilter: Linear,Linear\r\nrepeat: none\r\nbianzi\r\n  rotate: false\r\n  xy: 398, 30\r\n  size: 30, 96\r\n  orig: 30, 96\r\n  offset: 0, 0\r\n  index: -1\r\nbiyan2\r\n  rotate: false\r\n  xy: 170, 3\r\n  size: 23, 17\r\n  orig: 23, 17\r\n  offset: 0, 0\r\n  index: -1\r\nerhuan\r\n  rotate: false\r\n  xy: 385, 9\r\n  size: 9, 29\r\n  orig: 9, 29\r\n  offset: 0, 0\r\n  index: -1\r\nerhuan323\r\n  rotate: true\r\n  xy: 195, 3\r\n  size: 9, 29\r\n  orig: 9, 29\r\n  offset: 0, 0\r\n  index: -1\r\nfa565\r\n  rotate: true\r\n  xy: 218, 14\r\n  size: 34, 42\r\n  orig: 34, 42\r\n  offset: 0, 0\r\n  index: -1\r\nfayi1\r\n  rotate: true\r\n  xy: 307, 6\r\n  size: 32, 76\r\n  orig: 32, 76\r\n  offset: 0, 0\r\n  index: -1\r\nfs23\r\n  rotate: true\r\n  xy: 309, 40\r\n  size: 26, 83\r\n  orig: 26, 83\r\n  offset: 0, 0\r\n  index: -1\r\nhuahua\r\n  rotate: false\r\n  xy: 309, 68\r\n  size: 87, 58\r\n  orig: 87, 58\r\n  offset: 0, 0\r\n  index: -1\r\nlianlian\r\n  rotate: false\r\n  xy: 218, 50\r\n  size: 89, 76\r\n  orig: 89, 76\r\n  offset: 0, 0\r\n  index: -1\r\nshangbi1\r\n  rotate: true\r\n  xy: 109, 8\r\n  size: 32, 59\r\n  orig: 32, 59\r\n  offset: 0, 0\r\n  index: -1\r\nshenti\r\n  rotate: false\r\n  xy: 109, 42\r\n  size: 107, 84\r\n  orig: 107, 84\r\n  offset: 0, 0\r\n  index: -1\r\nshou1\r\n  rotate: true\r\n  xy: 396, 2\r\n  size: 26, 37\r\n  orig: 26, 37\r\n  offset: 0, 0\r\n  index: -1\r\ntoufa3\r\n  rotate: false\r\n  xy: 283, 9\r\n  size: 22, 39\r\n  orig: 22, 39\r\n  offset: 0, 0\r\n  index: -1\r\ntoufahoumian\r\n  rotate: true\r\n  xy: 2, 27\r\n  size: 99, 105\r\n  orig: 99, 105\r\n  offset: 0, 0\r\n  index: -1\r\nxiabi\r\n  rotate: true\r\n  xy: 2, 5\r\n  size: 20, 50\r\n  orig: 20, 50\r\n  offset: 0, 0\r\n  index: -1\r\nyoushang\r\n  rotate: true\r\n  xy: 435, 19\r\n  size: 49, 55\r\n  orig: 49, 55\r\n  offset: 0, 0\r\n  index: -1\r\nyoushou\r\n  rotate: false\r\n  xy: 54, 4\r\n  size: 40, 21\r\n  orig: 40, 21\r\n  offset: 0, 0\r\n  index: -1\r\nyouxia\r\n  rotate: true\r\n  xy: 492, 68\r\n  size: 58, 18\r\n  orig: 58, 18\r\n  offset: 0, 0\r\n  index: -1\r\nzuobi1\r\n  rotate: false\r\n  xy: 430, 70\r\n  size: 50, 56\r\n  orig: 50, 56\r\n  offset: 0, 0\r\n  index: -1\r\nzuoshou\r\n  rotate: false\r\n  xy: 170, 22\r\n  size: 43, 18\r\n  orig: 43, 18\r\n  offset: 0, 0\r\n  index: -1\r\nzuoxia\r\n  rotate: true\r\n  xy: 262, 2\r\n  size: 46, 19\r\n  orig: 46, 19\r\n  offset: 0, 0\r\n  index: -1\r\n",["qiuqiu_fapaiguan.png"],{"skeleton":{"hash":"/BjegWDJyp3f1d9SylDL8t3y4+E","spine":"3.6.53","width":142,"height":174,"images":"./images/"},"bones":[{"name":"root"},{"name":"bone","parent":"root"},{"name":"bone2","parent":"bone"},{"name":"shenti","parent":"bone2","length":56.8,"rotation":88.62,"x":0.02,"y":2.73},{"name":"lianlian","parent":"shenti","length":63.07,"rotation":0.88,"x":60.61,"y":0.36},{"name":"lianlian2","parent":"lianlian","x":55.45,"y":1.51},{"name":"bianzi","parent":"lianlian2","x":-38.38,"y":-25.48},{"name":"bianzi2","parent":"bianzi","length":28.63,"rotation":176.41,"x":-1.76,"y":0.44},{"name":"bianzi3","parent":"bianzi2","length":22.99,"rotation":7.27,"x":28.63},{"name":"bianzi4","parent":"bianzi3","length":21.29,"rotation":3.01,"x":22.99},{"name":"biyan2","parent":"lianlian","x":35.87,"y":20.02},{"name":"biyan3","parent":"lianlian","x":36.02,"y":-17.61,"scaleY":-1},{"name":"erhuan","parent":"lianlian","x":15.58,"y":33.04},{"name":"erhuan323","parent":"lianlian","x":22.88,"y":-32.64},{"name":"fa565","parent":"lianlian2","x":9.06,"y":-11.13},{"name":"fa566","parent":"fa565","length":16.5,"rotation":-131.69,"x":-1.39,"y":-2.12},{"name":"fa567","parent":"fa566","length":15.54,"rotation":-26.93,"x":16.5},{"name":"fa568","parent":"fa567","x":15.54},{"name":"fa569","parent":"fa568","length":15.25,"rotation":1.18,"x":-0.14,"y":-0.36},{"name":"fayi1","parent":"lianlian2","x":15.24,"y":23.04},{"name":"fayi2","parent":"fayi1","length":24.85,"rotation":163.32,"x":-3.49,"y":5.18},{"name":"fayi3","parent":"fayi2","length":18.96,"rotation":5.15,"x":25.75,"y":1.12},{"name":"fayi4","parent":"fayi3","length":16.22,"rotation":27.24,"x":18.96},{"name":"fayi5","parent":"fayi4","length":11.99,"rotation":35.45,"x":16.22},{"name":"fayi6","parent":"fayi5","length":9.79,"rotation":33.1,"x":11.99},{"name":"fs23","parent":"lianlian2","x":2.75,"y":-30.11},{"name":"fs24","parent":"fs23","length":19.2,"rotation":-168.84,"x":-6.55,"y":-0.17},{"name":"fs25","parent":"fs24","length":17.34,"rotation":2.66,"x":19.2},{"name":"fs26","parent":"fs25","length":17.89,"rotation":24.11,"x":17.34},{"name":"fs27","parent":"fs26","length":11.23,"rotation":-12.9,"x":17.89},{"name":"fs28","parent":"fs27","length":10.76,"rotation":-46.34,"x":11.34,"y":-0.29},{"name":"huahua","parent":"lianlian2","x":14.28,"y":18.8},{"name":"huahua2","parent":"huahua","length":17.76,"rotation":-105.23,"x":-2.73,"y":-4.87},{"name":"huahua3","parent":"huahua2","length":20.47,"rotation":11.54,"x":17.76},{"name":"huahua4","parent":"huahua","length":21.33,"rotation":159.52,"x":-5.45,"y":2.08},{"name":"huahua5","parent":"huahua4","length":17.02,"rotation":-25.21,"x":21.33},{"name":"shangbi1","parent":"shenti","length":45.9,"rotation":165.85,"x":41.5,"y":34.31},{"name":"xiabi","parent":"shangbi1","length":35.97,"rotation":21.62,"x":42.48,"y":-0.95},{"name":"shou1","parent":"xiabi","length":27.31,"rotation":-7.25,"x":34.1,"y":0.47},{"name":"toufa3","parent":"lianlian2","x":-29.6,"y":-32.38},{"name":"toufahoumian","parent":"lianlian2","x":20.16,"y":0.67},{"name":"youshang","parent":"shenti","length":51,"rotation":141.81,"x":40.22,"y":30.73},{"name":"youxia","parent":"youshang","length":43.17,"rotation":122.67,"x":50.06,"y":0.28},{"name":"youshou","parent":"youxia","length":25.97,"rotation":-5.24,"x":42.73,"y":-0.88},{"name":"youxia2","parent":"youshang","length":43.17,"rotation":122.67,"x":50.06,"y":0.28},{"name":"youshou4","parent":"youxia2","length":25.97,"rotation":-5.24,"x":42.73,"y":-0.88},{"name":"zuobi1","parent":"shenti","length":53.1,"rotation":-138.63,"x":42.83,"y":-27.37},{"name":"zuoxia","parent":"zuobi1","length":39.73,"rotation":-121.7,"x":58.1,"y":2.57},{"name":"zuoshou","parent":"zuoxia","length":24.3,"rotation":-7.01,"x":37.84,"y":0.28}],"slots":[{"name":"toufahoumian","bone":"toufahoumian","attachment":"toufahoumian"},{"name":"shenti","bone":"shenti","attachment":"shenti"},{"name":"youshang","bone":"youshang","attachment":"youshang"},{"name":"youxia","bone":"youxia","attachment":"xiabi"},{"name":"youshou","bone":"youshou"},{"name":"youshou4","bone":"youshou4","attachment":"youshou"},{"name":"youxia2","bone":"youxia2","attachment":"youxia"},{"name":"shangbi1","bone":"shangbi1"},{"name":"xiabi","bone":"xiabi"},{"name":"shou1","bone":"shou1"},{"name":"zuobi1","bone":"zuobi1","attachment":"zuobi1"},{"name":"bianzi","bone":"bianzi","attachment":"bianzi"},{"name":"zuoxia","bone":"zuoxia","attachment":"zuoxia"},{"name":"zuoshou","bone":"zuoshou","attachment":"zuoshou"},{"name":"lianlian","bone":"lianlian","attachment":"lianlian"},{"name":"biyan2","bone":"biyan2","attachment":"biyan2"},{"name":"biyan3","bone":"biyan3","attachment":"biyan2"},{"name":"toufa3","bone":"toufa3","attachment":"toufa3"},{"name":"erhuan","bone":"erhuan","attachment":"erhuan"},{"name":"fayi1","bone":"fayi1","attachment":"fayi1"},{"name":"erhuan323","bone":"erhuan323","attachment":"erhuan323"},{"name":"fs23","bone":"fs23","attachment":"fs23"},{"name":"fa565","bone":"fa565","attachment":"fa565"},{"name":"huahua","bone":"huahua","attachment":"huahua"}],"skins":{"default":{"bianzi":{"bianzi":{"type":"mesh","hull":15,"width":30,"height":96,"uvs":[0.60984,0.00367,0.24434,0.1232,0,0.18695,0,0.47383,0,0.70758,0.11684,0.89086,0.23584,1,0.60134,1,0.89034,0.92539,0.89034,0.78461,0.76284,0.7182,0.85634,0.50305,1,0.39414,1,0.17367,0.86484,0],"triangles":[7,10,8,7,6,10,6,5,10,10,9,8,5,4,10,10,4,3,10,3,1,10,1,11,11,1,0,12,11,13,13,11,0,3,2,1,13,0,14],"vertices":[1,7,-9.92,2.87,1,1,7,2.31,-7.25,1,1,7,8.93,-14.12,1,3,7,36.4,-12.16,0.19496,8,6.17,-13.05,0.80441,9,-17.48,-12.15,0.00063,2,8,28.58,-14.29,0.25233,9,4.83,-14.57,0.74767,1,9,22.7,-12.98,1,1,9,33.5,-10.56,1,1,9,34.69,0.34,1,1,9,28.5,9.73,1,1,9,15.06,11.19,1,2,8,30.86,8.5,0.02425,9,8.31,8.08,0.97575,2,7,37.37,13.66,0.13133,8,10.4,12.45,0.86867,2,7,26.64,17.22,0.60283,8,0.2,17.33,0.39717,2,7,5.52,15.71,0.99713,8,-20.94,18.5,0.00287,1,7,-10.82,10.48,1],"edges":[0,2,2,4,4,6,6,8,8,10,10,12,12,14,14,16,16,18,18,20,20,22,22,24,24,26,26,28,0,28]}},"biyan2":{"biyan2":{"type":"mesh","hull":14,"width":23,"height":17,"uvs":[0.34525,0,0.15082,0.04831,0,0.20513,0.01621,0.56431,0.08351,0.85266,0.25177,0.99936,0.42751,1,0.7042,1,0.92855,0.88301,1,0.7363,1,0.53395,0.93977,0.28607,0.81638,0.06854,0.60699,0],"triangles":[3,2,1,11,6,5,0,4,3,12,11,13,6,10,7,1,0,3,13,5,4,13,4,0,13,11,5,6,11,10,7,10,9,8,7,9],"vertices":[7.09,2.48,6.23,6.94,3.54,10.39,-2.56,9.96,-7.45,8.37,-9.91,4.48,-9.89,0.44,-9.83,-5.93,-7.8,-11.07,-5.29,-12.69,-1.85,-12.66,2.35,-11.24,6.02,-8.37,7.15,-3.54],"edges":[0,2,2,4,4,6,6,8,8,10,10,12,12,14,14,16,16,18,18,20,20,22,22,24,24,26,0,26]}},"biyan3":{"biyan2":{"type":"mesh","hull":14,"width":23,"height":17,"uvs":[0.34525,0,0.15082,0.04831,0,0.20513,0.01621,0.56431,0.08351,0.85266,0.25177,0.99936,0.42751,1,0.7042,1,0.92855,0.88301,1,0.7363,1,0.53395,0.93977,0.28607,0.81638,0.06854,0.60699,0],"triangles":[3,2,1,11,6,5,0,4,3,12,11,13,6,10,7,1,0,3,13,5,4,13,4,0,13,11,5,6,11,10,7,10,9,8,7,9],"vertices":[7.09,2.48,6.23,6.94,3.54,10.39,-2.56,9.96,-7.45,8.37,-9.91,4.48,-9.89,0.44,-9.83,-5.93,-7.8,-11.07,-5.29,-12.69,-1.85,-12.66,2.35,-11.24,6.02,-8.37,7.15,-3.54],"edges":[0,2,2,4,4,6,6,8,8,10,10,12,12,14,14,16,16,18,18,20,20,22,22,24,24,26,0,26]}},"erhuan":{"erhuan":{"x":-13.21,"y":-0.46,"rotation":-89.5,"width":9,"height":29}},"erhuan323":{"erhuan323":{"x":-19.96,"y":2.22,"rotation":-89.5,"width":9,"height":29}},"fa565":{"fa565":{"type":"mesh","hull":18,"width":34,"height":42,"uvs":[0.10644,0,0,0.03937,0,0.15306,0.23003,0.2804,0.4435,0.48959,0.52776,0.76244,0.67944,0.95344,0.73561,1,0.97717,1,0.94347,0.92161,0.78617,0.8443,0.75808,0.74425,0.90414,0.66694,0.70191,0.54871,0.6682,0.3668,0.62888,0.23947,0.39294,0.07575,0.24126,0],"triangles":[7,9,8,7,10,9,7,6,10,6,11,10,6,5,11,5,13,11,5,4,13,11,13,12,4,14,13,4,15,14,4,3,15,15,3,16,2,0,3,3,17,16,3,0,17,2,1,0],"vertices":[1,15,-4.05,1.91,1,1,15,-5.62,-1.74,1,1,15,-2.42,-5.28,1,1,15,6.97,-3.99,1,3,15,18.25,-5.63,0.12734,16,4.11,-4.23,0.87067,18,-11.37,-3.64,0.00198,2,16,15.84,-5.64,0.02491,18,0.33,-5.29,0.97509,1,18,9.7,-3.52,1,1,18,12.23,-2.49,1,1,18,15.32,5.13,1,1,18,11.84,5.3,1,2,16,22.18,1.35,0.00033,18,6.82,1.56,0.99967,2,16,17.92,1.95,0.52252,18,2.56,2.26,0.47748,1,16,16.65,7.75,1,1,16,9.56,3.1,1,2,15,20.45,3.32,0.1646,16,2.02,4.75,0.8354,2,15,15.86,6.39,0.86017,16,-3.46,5.41,0.13983,1,15,5.3,6.09,1,1,15,-0.65,4.99,1],"edges":[0,2,2,4,4,6,6,8,8,10,10,12,12,14,14,16,16,18,18,20,20,22,22,24,24,26,26,28,28,30,30,32,32,34,0,34]}},"fayi1":{"fayi1":{"type":"mesh","hull":18,"width":32,"height":76,"uvs":[0.7376,0.06771,0.56975,0.19699,0.42238,0.32627,0.38963,0.58137,0.35279,0.77787,0.45922,0.87612,0.71304,0.93472,0.9996,0.96747,0.93819,1,0.61888,1,0.48379,1,0.17266,0.92783,0,0.75718,0,0.46761,0.0171,0.23491,0.11944,0.07288,0.34051,0,0.79082,0],"triangles":[9,6,8,8,6,7,6,9,5,10,11,5,11,4,5,9,10,5,11,12,4,4,12,3,12,13,3,3,13,2,13,14,2,14,15,2,15,16,2,2,16,1,1,16,0,0,16,17],"vertices":[1,20,-4.06,7.85,1,1,20,6.92,5.62,1,2,20,17.7,4.01,0.9414,21,-7.76,3.61,0.0586,2,21,11.42,6.62,0.94243,22,-3.67,9.34,0.05757,3,21,26.28,8.58,0.00039,22,10.43,4.28,0.97328,23,-2.23,6.85,0.02633,3,22,18.53,5.61,0.07909,23,5.13,3.23,0.90222,24,-3.98,6.45,0.01869,2,23,14.24,4.94,0.02521,24,4.58,2.91,0.97479,1,24,13.97,1.43,1,1,24,12.28,-1.24,1,1,24,2.13,-2.35,1,2,23,11.71,-3.55,0.86342,24,-2.17,-2.82,0.13658,2,22,19.92,-4.27,0.29808,23,0.53,-5.62,0.70192,1,22,5.95,-6.2,1,2,20,31.95,-5.73,0.34085,21,5.57,-7.37,0.65915,1,20,14.89,-10.43,1,1,20,2.16,-10.93,1,1,20,-5.22,-5.81,1,1,20,-9.48,7.96,1],"edges":[0,2,2,4,4,6,6,8,8,10,10,12,12,14,14,16,16,18,18,20,20,22,22,24,24,26,26,28,28,30,30,32,32,34,0,34]}},"fs23":{"fs23":{"type":"mesh","hull":16,"width":26,"height":83,"uvs":[0.2156,0.02664,0.37783,0.13095,0.33514,0.28341,0.46321,0.46529,0.69375,0.62309,1,0.72473,1,0.94138,0.83037,1,0.64252,1,0.75352,0.87986,0.7706,0.78357,0.42052,0.68996,0.18145,0.54553,0.01922,0.3583,0,0.24864,0,0],"triangles":[8,9,7,7,9,6,9,10,6,10,5,6,10,4,5,11,4,10,11,3,4,11,12,3,12,2,3,12,13,2,13,14,2,14,0,2,2,0,1,14,15,0],"vertices":[1,26,-6.8,4.67,1,1,26,2.49,7.21,1,2,26,14.72,3.78,0.99287,27,-4.3,3.99,0.00713,2,27,11.15,3.75,0.98897,28,-4.11,5.95,0.01103,1,28,9.93,2.74,1,2,28,21.47,3.94,0.03888,29,2.6,4.64,0.96112,1,30,7.1,3.77,1,1,30,13.26,1.48,1,1,30,15.07,-3.06,1,2,29,11.66,-6.54,0.00595,30,4.74,-4.08,0.99405,3,28,21.72,-3.77,0.01158,29,4.57,-2.82,0.92317,30,-2.84,-6.64,0.06525,1,28,10.02,-6.27,1,2,27,15.95,-4.92,0.87593,28,-3.28,-3.92,0.12407,2,26,19.31,-5.44,0.5033,27,-0.15,-5.44,0.4967,1,26,10.27,-4.25,1,1,26,-10.01,-0.43,1],"edges":[0,2,2,4,4,6,6,8,8,10,10,12,12,14,14,16,16,18,18,20,20,22,22,24,24,26,26,28,28,30,0,30]}},"huahua":{"huahua":{"type":"mesh","hull":28,"width":87,"height":58,"uvs":[0.4492,0.37793,0.53044,0.48696,0.69863,0.52117,0.88106,0.49124,0.98938,0.68792,1,0.64944,0.98083,0.42924,1,0.31806,0.94235,0.30096,0.85256,0.17055,0.71288,0.09358,0.53472,0.10213,0.38364,0.15986,0.38079,0.038,0.31522,0,0.10998,0,0.10286,0.16413,0,0.27103,0,0.45061,0.04015,0.55751,0.08433,0.69648,0.1841,0.6302,0.18267,0.78413,0.07293,0.84613,0.0886,0.97227,0.26391,1,0.31522,0.84185,0.41357,0.60455],"triangles":[22,21,26,24,23,22,25,22,26,24,22,25,18,17,16,16,15,14,14,12,16,0,19,18,12,0,16,0,18,16,13,12,14,27,21,0,21,19,0,20,19,21,26,21,27,6,8,7,8,2,9,3,8,6,2,10,9,3,2,8,3,6,5,4,3,5,0,12,11,10,1,0,11,10,0,2,1,10],"vertices":[2,32,-0.72,-5.29,0.50211,34,0.35,5.33,0.49789,3,32,7.8,-9.46,0.99874,33,-11.65,-7.27,0.00015,34,3.73,14.19,0.0011,2,32,22.42,-7.4,0.17886,33,3.08,-8.18,0.82114,1,33,18.79,-5.29,1,1,33,29.02,-15.98,1,1,33,29.78,-13.69,1,1,33,27.18,-1.07,1,1,33,28.37,5.48,1,2,32,39.37,10.64,0.00042,33,23.3,6.1,0.99958,2,32,29.8,15.8,0.0764,33,14.96,13.07,0.9236,2,32,16.89,16.81,0.50843,33,2.51,16.64,0.49157,3,32,2.11,12.13,0.9778,33,-12.91,15.01,0.02212,34,-17.25,6.55,0.00008,3,32,-9.64,5.34,0.27868,34,-9.41,-4.52,0.72132,35,-25.89,-17.19,0.00001,2,32,-11.79,12.08,0.06794,34,-15.93,-7.29,0.93206,3,32,-17.88,12.65,0.02956,34,-15.94,-13.4,0.9697,35,-28.02,-28,0.00074,2,34,-9.55,-30.07,0.98125,35,-15.13,-40.36,0.01875,2,34,-0.44,-27.25,0.94412,35,-8.09,-33.92,0.05588,2,34,8.55,-33.38,0.87252,35,2.66,-35.65,0.12748,2,34,18.28,-29.65,0.80996,35,9.87,-28.13,0.19004,2,34,22.82,-24.17,0.74108,35,11.64,-21.24,0.25892,2,34,28.97,-17.7,0.66606,35,14.45,-12.76,0.33394,2,34,22.27,-10.97,0.50224,35,5.52,-9.53,0.49776,2,34,30.65,-7.89,0.00824,35,11.79,-3.17,0.99176,1,35,21.17,-7.18,1,1,35,25.25,-0.96,1,1,35,15.36,10.76,1,1,35,5.79,7.23,1,1,34,13.74,7.14,1],"edges":[0,2,2,4,4,6,6,8,8,10,10,12,12,14,14,16,16,18,18,20,20,22,22,24,24,26,26,28,28,30,30,32,32,34,34,36,36,38,38,40,40,42,42,44,44,46,46,48,48,50,50,52,52,54,0,54]}},"lianlian":{"lianlian":{"x":33.15,"y":0.85,"rotation":-89.5,"width":89,"height":76}},"shenti":{"shenti":{"type":"mesh","hull":20,"width":107,"height":84,"uvs":[0.52438,0,0.53778,0.11005,0.48641,0.16411,0.40153,0.18402,0.32112,0.21532,0.32413,0.30607,0.32782,0.41733,0.35463,0.49415,0.33899,0.65918,0.41047,0.86688,0.89963,0.86972,0.95101,0.74169,0.97781,0.56528,0.95101,0.49415,0.98228,0.38319,1,0.22386,0.93537,0.16411,0.79912,0.15557,0.74551,0.12143,0.75891,0,0.50138,0.4313,0.75045,0.42821,0.54876,0.32452,0.75531,0.32142,0.5111,0.68975,0.76381,0.68511],"triangles":[1,0,19,18,1,19,5,4,3,23,18,17,22,1,18,22,18,23,2,1,22,3,2,22,5,3,22,15,23,16,23,17,16,15,14,23,20,6,5,21,22,23,21,23,14,22,20,5,20,22,21,7,6,20,13,21,14,25,21,13,25,13,12,24,20,21,24,21,25,7,20,24,8,7,24,11,25,12,9,8,24,10,25,11,9,24,25,10,9,25],"vertices":[65.43,14.43,56.23,12.78,51.55,18.16,49.66,27.2,46.83,35.74,39.22,35.24,29.88,34.62,23.5,31.6,9.6,32.93,-7.66,24.87,-6.64,-27.46,4.25,-32.7,19.13,-35.21,25.03,-32.2,34.43,-35.32,47.86,-36.89,52.71,-29.86,53.07,-15.27,55.8,-9.46,66.04,-10.65,29.15,16.02,30.06,-10.61,38.24,11.17,39.03,-10.92,7.48,14.46,8.52,-12.56],"edges":[0,2,2,4,4,6,6,8,12,14,14,16,16,18,18,20,20,22,22,24,24,26,26,28,28,30,30,32,32,34,34,36,36,38,0,38,12,40,40,42,42,26,8,10,10,12,10,44,44,46,46,28,2,44,16,48,48,50,50,22]}},"toufa3":{"toufa3":{"x":-11.86,"y":-7.95,"rotation":-89.5,"width":22,"height":39}},"toufahoumian":{"toufahoumian":{"x":-32.98,"y":0.75,"rotation":-89.5,"width":99,"height":105}},"youshang":{"shangbi1":{"x":20.89,"y":3,"rotation":116.24,"width":32,"height":59},"youshang":{"type":"mesh","hull":16,"width":49,"height":55,"uvs":[0.88902,0,0.73906,0,0.64704,0.0341,0.49367,0.2345,0.30622,0.4683,0.11196,0.7021,0,0.86606,0.0029,0.96626,0.09151,1,0.30963,1,0.47322,0.8691,0.57547,0.72943,0.78336,0.55635,0.95036,0.35292,0.99467,0.21932,0.98445,0.04321],"triangles":[0,14,1,14,0,15,1,13,2,14,13,1,13,3,2,12,3,13,4,3,12,11,4,12,10,5,4,11,10,4,6,8,7,5,8,6,8,5,9,10,9,5],"vertices":[-8.79,-1.62,-4.11,-7.28,0.21,-9.57,13.49,-8.34,29.25,-7.23,45.23,-6.37,55.67,-4.86,59.83,-1.24,58.5,3.29,51.69,11.53,41.03,13.12,31.92,12.09,18.09,13.88,4.25,13.06,-2.79,10.05,-9.94,3.5],"edges":[0,2,2,4,4,6,6,8,8,10,10,12,12,14,14,16,16,18,18,20,20,22,22,24,24,26,26,28,28,30,0,30]}},"youshou":{"shou1":{"x":16.81,"y":5.15,"rotation":101.45,"width":26,"height":37}},"youshou4":{"youshou":{"type":"mesh","hull":17,"width":40,"height":21,"uvs":[0.40108,0.0416,0.22453,0,0.14203,0,0.06613,0.16731,0,0.40931,0.09418,0.65445,0.29548,0.80845,0.48853,0.86817,0.64693,1,0.78718,0.96245,0.92578,0.89331,0.97693,0.77703,1,0.61045,0.99178,0.44703,0.88618,0.28045,0.91093,0.10131,0.63208,0.09817,0.18839,0.18418,0.13632,0.46062,0.37754,0.21028,0.3327,0.53454,0.61437,0.24295,0.59095,0.63174],"triangles":[17,2,1,17,1,0,3,2,17,19,17,0,19,0,16,21,19,16,14,16,15,21,16,14,17,4,3,18,4,17,19,18,17,20,18,19,21,20,19,22,21,14,22,14,13,22,13,12,22,20,21,5,4,18,5,18,20,11,22,12,6,5,20,6,20,22,7,6,22,11,9,22,9,7,22,11,10,9,8,7,9],"vertices":[9.74,7.93,2.65,7.3,-0.58,6.61,-2.81,2.54,-4.32,-2.99,0.44,-7.23,8.99,-8.7,16.81,-8.3,23.58,-9.68,28.9,-7.73,34.02,-5.14,35.5,-2.32,35.67,1.29,34.63,4.58,29.76,7.11,29.94,11,19.02,8.71,2.05,3.22,1.23,-2.9,9.56,4.27,9.24,-2.76,18.97,5.59,19.77,-2.59],"edges":[0,2,2,4,4,6,6,8,8,10,10,12,12,14,14,16,16,18,18,20,20,22,22,24,24,26,26,28,28,30,30,32,0,32,6,34,2,34,8,36,34,36,36,10,38,34,0,38,40,36,38,40,40,12,28,42,42,38,32,42,22,44,44,40,42,44]}},"youxia":{"xiabi":{"type":"mesh","hull":19,"width":20,"height":50,"uvs":[0.10184,0.02829,0.35859,0,0.71014,0,0.89184,0.07252,0.99058,0.17364,1,0.33006,0.97478,0.52282,0.97478,0.69346,0.99848,0.88622,1,0.9747,0.82864,0.99524,0.56004,1,0.36254,0.97154,0.30724,0.82934,0.22034,0.68714,0.10184,0.50544,0.02679,0.3901,0,0.2795,0,0.07568,0.72601,0.35167,0.73645,0.6699,0.42469,0.36939,0.5428,0.68543],"triangles":[17,18,0,19,2,3,19,3,4,19,4,5,21,1,2,21,2,19,21,16,17,21,15,16,0,1,21,0,21,17,6,19,5,20,19,6,22,21,19,20,22,19,14,15,21,22,14,21,20,6,7,13,14,22,12,13,22,8,10,20,8,20,7,10,8,9,11,22,20,11,20,10,12,22,11],"vertices":[-6.53,-8.43,-7.55,-3.2,-7,3.81,-3.11,7.15,2.09,8.73,9.9,8.31,19.47,7.06,27.98,6.4,37.62,6.13,42.04,5.82,42.79,2.32,42.62,-3.05,40.89,-6.88,33.72,-7.43,26.49,-8.62,17.25,-10.28,11.39,-11.33,5.83,-11.43,-4.33,-10.64,10.55,2.76,26.43,1.74,10.97,-3.31,26.91,-2.18],"edges":[0,2,2,4,4,6,6,8,8,10,10,12,12,14,14,16,16,18,18,20,20,22,22,24,24,26,26,28,28,30,30,32,32,34,34,36,0,36,4,38,38,40,40,20,2,42,42,44,44,22]}},"youxia2":{"youxia":{"type":"mesh","hull":13,"width":58,"height":18,"uvs":[0.45903,0.00995,0.21584,0.00002,0.03404,0.0924,0,0.40484,0.01724,0.75078,0.09782,1,0.25101,1,0.58165,1,0.94075,1,0.98276,0.77195,0.98276,0.4474,0.88382,0.29923,0.65391,0.16517,0.22777,0.51524,0.48835,0.54824],"triangles":[13,1,0,14,13,0,2,1,13,3,2,13,12,14,0,14,12,11,4,3,13,14,11,10,9,14,10,6,5,4,6,13,14,6,4,13,7,14,9,6,14,7,8,7,9],"vertices":[17.32,7.35,3.3,5.83,-6.97,2.91,-8.25,-2.91,-6.51,-8.97,-1.33,-12.86,7.49,-11.79,26.53,-9.49,47.2,-6.99,49.13,-2.62,48.43,3.18,42.41,5.14,28.88,5.93,5.1,-3.29,20.18,-2.07],"edges":[0,2,2,4,4,6,6,8,8,10,10,12,12,14,14,16,16,18,18,20,20,22,22,24,0,24,8,26,26,28]}},"zuobi1":{"zuobi1":{"x":27.61,"y":1.17,"rotation":50.01,"width":50,"height":56}},"zuoshou":{"zuoshou":{"x":18.81,"y":1.38,"rotation":178.71,"width":43,"height":18}},"zuoxia":{"zuoxia":{"x":18.77,"y":-0.68,"rotation":171.7,"width":46,"height":19}}}},"animations":{"daiji":{"slots":{"biyan2":{"color":[{"time":0,"color":"ffffff00","curve":"stepped"},{"time":0.8,"color":"ffffff00","curve":[0.25,0,0.75,1]},{"time":0.8667,"color":"ffffffff","curve":"stepped"},{"time":1.0667,"color":"ffffffff","curve":[0.25,0,0.75,1]},{"time":1.1333,"color":"ffffff00"}]},"biyan3":{"color":[{"time":0,"color":"ffffff00","curve":"stepped"},{"time":0.8,"color":"ffffff00","curve":[0.25,0,0.75,1]},{"time":0.8667,"color":"ffffffff","curve":"stepped"},{"time":1.0667,"color":"ffffffff","curve":[0.25,0,0.75,1]},{"time":1.1333,"color":"ffffff00"}]},"shangbi1":{"attachment":[{"time":0,"name":null}]},"shou1":{"attachment":[{"time":0,"name":null}]},"xiabi":{"attachment":[{"time":0,"name":null}]},"youshou":{"attachment":[{"time":0,"name":null}]},"youxia":{"attachment":[{"time":0,"name":null}]}},"bones":{"bianzi2":{"rotate":[{"time":0,"angle":0,"curve":"stepped"},{"time":2.6667,"angle":0}]},"bianzi3":{"rotate":[{"time":0,"angle":0,"curve":"stepped"},{"time":2.6667,"angle":0}]},"bianzi4":{"rotate":[{"time":0,"angle":0,"curve":"stepped"},{"time":2.6667,"angle":0}]},"erhuan323":{"rotate":[{"time":0,"angle":4.08,"curve":[0.25,0,0.75,1]},{"time":1.3333,"angle":-4.62,"curve":[0.25,0,0.75,1]},{"time":2.6667,"angle":4.08}]},"erhuan":{"rotate":[{"time":0,"angle":-1.17,"curve":[0.375,0.5,0.75,1]},{"time":0.6667,"angle":-7.77,"curve":[0.25,0,0.75,1]},{"time":2,"angle":5.42,"curve":[0.25,0,0.625,0.5]},{"time":2.6667,"angle":-1.17}]},"fs24":{"rotate":[{"time":0,"angle":2.18,"curve":[0.375,0.5,0.75,1]},{"time":0.6667,"angle":4.35,"curve":[0.25,0,0.75,1]},{"time":2,"angle":0,"curve":[0.25,0,0.75,1]},{"time":2.6667,"angle":2.18}]},"fs25":{"rotate":[{"time":0,"angle":0,"curve":[0.25,0,0.75,1]},{"time":1.3333,"angle":-5.2,"curve":[0.25,0,0.75,1]},{"time":2.6667,"angle":0}]},"fs26":{"rotate":[{"time":0,"angle":-9.09,"curve":[0.25,0,0.75,1]},{"time":1.3333,"angle":-0.32,"curve":[0.25,0,0.75,1]},{"time":2.6667,"angle":-9.09}]},"toufa3":{"rotate":[{"time":0,"angle":0,"curve":[0.25,0,0.75,1]},{"time":1.3333,"angle":8.96,"curve":[0.25,0,0.75,1]},{"time":2.6667,"angle":0}]},"fa566":{"rotate":[{"time":0,"angle":1.05,"curve":[0.327,0.31,0.758,1]},{"time":1.0333,"angle":6.65,"curve":[0.25,0,0.75,1]},{"time":2.3667,"angle":0,"curve":[0.25,0,0.75,1]},{"time":2.6667,"angle":1.05}]},"fa567":{"rotate":[{"time":0,"angle":3.32,"curve":[0.375,0.5,0.75,1]},{"time":0.6667,"angle":6.65,"curve":[0.25,0,0.75,1]},{"time":2,"angle":0,"curve":[0.25,0,0.75,1]},{"time":2.6667,"angle":3.32}]},"fa569":{"rotate":[{"time":0,"angle":0,"curve":[0.25,0,0.75,1]},{"time":1.3333,"angle":6.65,"curve":[0.25,0,0.75,1]},{"time":2.6667,"angle":0}]},"fs28":{"rotate":[{"time":0,"angle":-4.23},{"time":0.7333,"angle":0},{"time":2.0667,"angle":-7.69},{"time":2.6667,"angle":-4.23}]},"fs27":{"rotate":[{"time":0,"angle":-12.5,"curve":[0.298,0.2,0.756,1]},{"time":1.1667,"angle":0,"curve":[0.25,0,0.75,1]},{"time":2.5,"angle":-13.33,"curve":[0.299,0,0.636,0.36]},{"time":2.6667,"angle":-12.5}]},"fayi2":{"rotate":[{"time":0,"angle":0,"curve":[0.25,0,0.75,1]},{"time":1.3333,"angle":5.61,"curve":[0.25,0,0.75,1]},{"time":2.6667,"angle":0}]},"fayi6":{"rotate":[{"time":0,"angle":0,"curve":[0.25,0,0.75,1]},{"time":1.3333,"angle":3.2,"curve":[0.25,0,0.75,1]},{"time":2.6667,"angle":0}]},"fayi5":{"rotate":[{"time":0,"angle":0,"curve":[0.25,0,0.75,1]},{"time":1.3333,"angle":3.2,"curve":[0.25,0,0.75,1]},{"time":2.6667,"angle":0}]},"fayi4":{"rotate":[{"time":0,"angle":2.33,"curve":[0.382,0.57,0.734,1]},{"time":0.4333,"angle":3.2,"curve":[0.25,0,0.75,1]},{"time":1.7667,"angle":0,"curve":[0.25,0,0.75,1]},{"time":2.6667,"angle":2.33}]},"fayi3":{"rotate":[{"time":0,"angle":0.88,"curve":[0.35,0.39,0.757,1]},{"time":0.9,"angle":3.2,"curve":[0.25,0,0.75,1]},{"time":2.2333,"angle":0,"curve":[0.25,0,0.75,1]},{"time":2.6667,"angle":0.88}]},"huahua2":{"rotate":[{"time":0,"angle":0,"curve":[0.25,0,0.75,1]},{"time":1.3333,"angle":2.07,"curve":[0.25,0,0.75,1]},{"time":2.6667,"angle":0}]},"huahua3":{"rotate":[{"time":0,"angle":0,"curve":[0.25,0,0.75,1]},{"time":1.3333,"angle":-9.95,"curve":[0.25,0,0.75,1]},{"time":2.6667,"angle":0}]},"huahua4":{"rotate":[{"time":0,"angle":0,"curve":[0.25,0,0.75,1]},{"time":1.3333,"angle":-2.41,"curve":[0.25,0,0.75,1]},{"time":2.6667,"angle":0}]},"huahua5":{"rotate":[{"time":0,"angle":0,"curve":[0.25,0,0.75,1]},{"time":1.3333,"angle":-12.17,"curve":[0.25,0,0.75,1]},{"time":2.6667,"angle":0}]},"shenti":{"scale":[{"time":0,"x":1,"y":1,"curve":"stepped"},{"time":2.6667,"x":1,"y":1}]},"youshang":{"rotate":[{"time":0,"angle":0},{"time":1.3333,"angle":2.35},{"time":2.6667,"angle":0}],"translate":[{"time":0,"x":0,"y":0},{"time":1.3333,"x":0.9,"y":0},{"time":2.6667,"x":0,"y":0}]},"youxia":{"rotate":[{"time":0,"angle":0},{"time":1.3333,"angle":-1.08},{"time":2.6667,"angle":0}]},"youshou":{"rotate":[{"time":0,"angle":0},{"time":1.3333,"angle":-2.75},{"time":2.6667,"angle":0}],"translate":[{"time":0,"x":0,"y":0},{"time":1.3333,"x":-1.13,"y":0.43},{"time":2.6667,"x":0,"y":0}]},"zuobi1":{"rotate":[{"time":0,"angle":0},{"time":1.3333,"angle":-1.64},{"time":2.6667,"angle":0}]},"zuoxia":{"rotate":[{"time":0,"angle":0},{"time":1.3333,"angle":0.87},{"time":2.6667,"angle":0}],"translate":[{"time":0,"x":0,"y":0},{"time":1.3333,"x":-0.49,"y":0.39},{"time":2.6667,"x":0,"y":0}]},"zuoshou":{"rotate":[{"time":0,"angle":0,"curve":"stepped"},{"time":2.6667,"angle":0}],"translate":[{"time":0,"x":0,"y":0},{"time":1.3333,"x":-0.89,"y":0.12},{"time":2.6667,"x":0,"y":0}]},"youshou4":{"rotate":[{"time":0,"angle":0},{"time":1.3333,"angle":-2.75},{"time":2.6667,"angle":0}],"translate":[{"time":0,"x":0,"y":0},{"time":1.3333,"x":-1.13,"y":0.43},{"time":2.6667,"x":0,"y":0}]},"youxia2":{"rotate":[{"time":0,"angle":0},{"time":1.3333,"angle":-1.08},{"time":2.6667,"angle":0}]}},"deform":{"default":{"biyan2":{"biyan2":[{"time":0.8,"offset":6,"vertices":[6.7393,-2.05674,11.79008,-4.5511,13.85795,-4.5332,13.06533,-5.2451,11.53319,-2.01524,7.64255,2.18123,5.47935,2.30352,4.52827,3.61131,3.26009,3.50633,0.92023,2.31104],"curve":[0.25,0,0.75,1]},{"time":0.9333,"curve":"stepped"},{"time":1,"curve":[0.25,0,0.75,1]},{"time":1.1333,"offset":6,"vertices":[6.7393,-2.05674,11.79008,-4.5511,13.85795,-4.5332,13.06533,-5.2451,11.53319,-2.01524,7.64255,2.18123,5.47935,2.30352,4.52827,3.61131,3.26009,3.50633,0.92023,2.31104]}]},"biyan3":{"biyan2":[{"time":0.8,"offset":6,"vertices":[6.7393,-2.05674,11.79008,-4.5511,13.85795,-4.5332,13.06533,-5.2451,11.53319,-2.01524,7.64255,2.18123,5.47935,2.30352,4.52827,3.61131,3.26009,3.50633,0.92023,2.31104],"curve":[0.25,0,0.75,1]},{"time":0.9333,"curve":"stepped"},{"time":1,"curve":[0.25,0,0.75,1]},{"time":1.1333,"offset":6,"vertices":[6.7393,-2.05674,11.79008,-4.5511,13.85795,-4.5332,13.06533,-5.2451,11.53319,-2.01524,7.64255,2.18123,5.47935,2.30352,4.52827,3.61131,3.26009,3.50633,0.92023,2.31104]}]},"youxia2":{"youxia":[{"time":0,"offset":4,"vertices":[3.30504,-0.5751,1.78791,-1.95537,2.50494,-0.03939,1.72955,2.60464,0.47128,0.93337]}]}}}},"fapai":{"slots":{"biyan2":{"color":[{"time":0,"color":"ffffff00","curve":"stepped"},{"time":0.3333,"color":"ffffff00","curve":[0.25,0,0.75,1]},{"time":0.3667,"color":"ffffffff","curve":"stepped"},{"time":0.5,"color":"ffffffff","curve":[0.25,0,0.75,1]},{"time":0.5333,"color":"ffffff00"}]},"biyan3":{"color":[{"time":0,"color":"ffffff00","curve":"stepped"},{"time":0.3333,"color":"ffffff00","curve":[0.25,0,0.75,1]},{"time":0.3667,"color":"ffffffff","curve":"stepped"},{"time":0.5,"color":"ffffffff","curve":[0.25,0,0.75,1]},{"time":0.5333,"color":"ffffff00"}]},"shangbi1":{"attachment":[{"time":0,"name":null}]},"shou1":{"attachment":[{"time":0,"name":null}]},"xiabi":{"attachment":[{"time":0,"name":null}]},"youshou":{"color":[{"time":0,"color":"ffffff00","curve":"stepped"},{"time":0.8667,"color":"ffffff00"}],"attachment":[{"time":0,"name":"shou1"},{"time":1.1333,"name":"shou1"}]},"youshou4":{"color":[{"time":0,"color":"ffffffff"}],"attachment":[{"time":0,"name":"youshou"},{"time":1.4667,"name":"youshou"}]},"youxia":{"color":[{"time":0,"color":"ffffff00","curve":"stepped"},{"time":0.0333,"color":"ffffff00","curve":[0.25,0,0.75,1]},{"time":0.5333,"color":"ffffffda","curve":[0.25,0,0.75,1]},{"time":0.8667,"color":"ffffffe7","curve":[0.25,0,0.75,1]},{"time":1.3,"color":"ffffff58","curve":[0.25,0,0.75,1]},{"time":1.6333,"color":"ffffff00"}]},"youxia2":{"attachment":[{"time":0,"name":"youxia"}]}},"bones":{"shou1":{"rotate":[{"time":0.7333,"angle":0}],"translate":[{"time":0.7333,"x":0,"y":0}]},"xiabi":{"rotate":[{"time":0.4667,"angle":63.57,"curve":[0.25,0,0.75,1]},{"time":0.5333,"angle":13.12,"curve":[0.25,0,0.75,1]},{"time":0.7333,"angle":0,"curve":[0.25,0,0.75,1]},{"time":1.1,"angle":63.57}],"translate":[{"time":0.7333,"x":0,"y":0}]},"shangbi1":{"rotate":[{"time":0.4667,"angle":8.18,"curve":[0.25,0,0.75,1]},{"time":0.5333,"angle":-321.19,"curve":[0.25,0,0.75,1]},{"time":0.7333,"angle":0,"curve":[0.25,0,0.75,1]},{"time":1.1,"angle":8.18}],"translate":[{"time":0.4667,"x":-0.93,"y":-4.72,"curve":[0.25,0,0.75,1]},{"time":0.5333,"x":-2.05,"y":-1.62,"curve":[0.25,0,0.75,1]},{"time":0.7333,"x":0,"y":0,"curve":[0.25,0,0.75,1]},{"time":1.1,"x":-0.93,"y":-4.72}]},"bianzi2":{"rotate":[{"time":0,"angle":0,"curve":"stepped"},{"time":1.6667,"angle":0}]},"bianzi3":{"rotate":[{"time":0,"angle":0,"curve":"stepped"},{"time":1.6667,"angle":0}]},"bianzi4":{"rotate":[{"time":0,"angle":0,"curve":"stepped"},{"time":1.6667,"angle":0}]},"erhuan323":{"rotate":[{"time":0,"angle":4.08,"curve":[0.25,0,0.75,1]},{"time":0.5333,"angle":-4.62,"curve":[0.25,0,0.75,1]},{"time":1.6667,"angle":4.08}]},"erhuan":{"rotate":[{"time":0,"angle":-1.17,"curve":[0.25,0,0.75,1]},{"time":0.2333,"angle":-7.77,"curve":[0.25,0,0.75,1]},{"time":1.1333,"angle":5.42,"curve":[0.25,0,0.75,1]},{"time":1.6667,"angle":-1.17}]},"fs24":{"rotate":[{"time":0,"angle":2.18,"curve":[0.25,0,0.75,1]},{"time":0.2333,"angle":4.35,"curve":[0.25,0,0.75,1]},{"time":1.1333,"angle":0,"curve":[0.25,0,0.75,1]},{"time":1.6667,"angle":2.18}]},"fs25":{"rotate":[{"time":0,"angle":0,"curve":[0.25,0,0.75,1]},{"time":0.5333,"angle":-5.2,"curve":[0.25,0,0.75,1]},{"time":1.6667,"angle":0}]},"fs26":{"rotate":[{"time":0,"angle":-9.09,"curve":[0.25,0,0.75,1]},{"time":0.5333,"angle":-0.32,"curve":[0.25,0,0.75,1]},{"time":1.6667,"angle":-9.09}]},"toufa3":{"rotate":[{"time":0,"angle":0,"curve":[0.25,0,0.75,1]},{"time":0.5333,"angle":8.96,"curve":[0.25,0,0.75,1]},{"time":1.6667,"angle":0}]},"fa566":{"rotate":[{"time":0,"angle":1.05,"curve":[0.25,0,0.75,1]},{"time":0.4667,"angle":6.65,"curve":[0.25,0,0.75,1]},{"time":1.4333,"angle":0,"curve":[0.25,0,0.75,1]},{"time":1.6667,"angle":1.05}]},"fa567":{"rotate":[{"time":0,"angle":3.32,"curve":[0.25,0,0.75,1]},{"time":0.2333,"angle":6.65,"curve":[0.25,0,0.75,1]},{"time":1.1333,"angle":0,"curve":[0.25,0,0.75,1]},{"time":1.6667,"angle":3.32}]},"fa569":{"rotate":[{"time":0,"angle":0,"curve":[0.25,0,0.75,1]},{"time":0.5333,"angle":6.65,"curve":[0.25,0,0.75,1]},{"time":1.6667,"angle":0}]},"fs28":{"rotate":[{"time":0,"angle":-4.23,"curve":[0.25,0,0.75,1]},{"time":0.3,"angle":0,"curve":[0.25,0,0.75,1]},{"time":1.1667,"angle":-7.69,"curve":[0.25,0,0.75,1]},{"time":1.6667,"angle":-4.23}]},"fs27":{"rotate":[{"time":0,"angle":-12.5,"curve":[0.25,0,0.75,1]},{"time":0.6,"angle":0,"curve":[0.25,0,0.75,1]},{"time":1.5333,"angle":-13.33,"curve":[0.25,0,0.75,1]},{"time":1.6667,"angle":-12.5}]},"fayi2":{"rotate":[{"time":0,"angle":0,"curve":[0.25,0,0.75,1]},{"time":0.5333,"angle":5.61,"curve":[0.25,0,0.75,1]},{"time":1.6667,"angle":0}]},"fayi6":{"rotate":[{"time":0,"angle":0,"curve":[0.25,0,0.75,1]},{"time":0.5333,"angle":3.2,"curve":[0.25,0,0.75,1]},{"time":1.6667,"angle":0}]},"fayi5":{"rotate":[{"time":0,"angle":0,"curve":[0.25,0,0.75,1]},{"time":0.5333,"angle":3.2,"curve":[0.25,0,0.75,1]},{"time":1.6667,"angle":0}]},"fayi4":{"rotate":[{"time":0,"angle":2.33,"curve":[0.25,0,0.75,1]},{"time":0.1667,"angle":3.2,"curve":[0.25,0,0.75,1]},{"time":1,"angle":0,"curve":[0.25,0,0.75,1]},{"time":1.6667,"angle":2.33}]},"fayi3":{"rotate":[{"time":0,"angle":0.88,"curve":[0.25,0,0.75,1]},{"time":0.4,"angle":3.2,"curve":[0.25,0,0.75,1]},{"time":1.3,"angle":0,"curve":[0.25,0,0.75,1]},{"time":1.6667,"angle":0.88}]},"huahua2":{"rotate":[{"time":0,"angle":0,"curve":[0.25,0,0.75,1]},{"time":0.5333,"angle":2.07,"curve":[0.25,0,0.75,1]},{"time":1.6667,"angle":0}]},"huahua3":{"rotate":[{"time":0,"angle":0,"curve":[0.25,0,0.75,1]},{"time":0.5333,"angle":-9.95,"curve":[0.25,0,0.75,1]},{"time":1.6667,"angle":0}]},"huahua4":{"rotate":[{"time":0,"angle":0,"curve":[0.25,0,0.75,1]},{"time":0.5333,"angle":-2.41,"curve":[0.25,0,0.75,1]},{"time":1.6667,"angle":0}]},"huahua5":{"rotate":[{"time":0,"angle":0,"curve":[0.25,0,0.75,1]},{"time":0.5333,"angle":-12.17,"curve":[0.25,0,0.75,1]},{"time":1.6667,"angle":0}]},"shenti":{"scale":[{"time":0,"x":1,"y":1,"curve":"stepped"},{"time":1.6667,"x":1,"y":1}]},"youshang":{"rotate":[{"time":0,"angle":0,"curve":[0.25,0,0.75,1]},{"time":0.2,"angle":8.42,"curve":[0.25,0,0.75,1]},{"time":0.5333,"angle":-314.45,"curve":[0.25,0,0.75,1]},{"time":1.1333,"angle":2.25,"curve":[0.25,0,0.75,1]},{"time":1.2667,"angle":0}],"translate":[{"time":0,"x":0,"y":0,"curve":[0.25,0,0.75,1]},{"time":0.5333,"x":-0.38,"y":0.94,"curve":[0.25,0,0.75,1]},{"time":1.2667,"x":0,"y":0}]},"youxia":{"rotate":[{"time":0,"angle":0,"curve":[0.25,0,0.75,1]},{"time":0.2,"angle":-27.02,"curve":[0.25,0,0.75,1]},{"time":0.5333,"angle":-64.21,"curve":[0.25,0,0.75,1]},{"time":0.8667,"angle":-76.78,"curve":[0.265,0,0.618,0.43]},{"time":1.0667,"angle":-49.66,"curve":[0.327,0.31,0.683,0.72]},{"time":1.3,"angle":-7.65,"curve":[0.381,0.59,0.728,1]},{"time":1.4667,"angle":0.98}],"translate":[{"time":0,"x":0,"y":0,"curve":[0.25,0,0.75,1]},{"time":0.2,"x":-2.4,"y":1.24,"curve":[0.25,0,0.75,1]},{"time":0.5333,"x":-6.15,"y":3.3,"curve":[0.25,0,0.75,1]},{"time":0.7333,"x":-10.74,"y":2.26,"curve":[0.25,0,0.75,1]},{"time":0.8667,"x":-11.25,"y":1.65,"curve":[0.243,0,0.654,0.62]},{"time":1.1667,"x":-7.14,"y":-0.35,"curve":[0.352,0.4,0.689,0.75]},{"time":1.2333,"x":-4.21,"y":-1.68,"curve":[0.369,0.63,0.707,1]},{"time":1.3,"x":-1.16,"y":0.75,"curve":[0.25,0,0.75,1]},{"time":1.4667,"x":0,"y":0}],"scale":[{"time":0,"x":1,"y":1,"curve":[0.25,0,0.75,1]},{"time":0.5333,"x":0.883,"y":1,"curve":[0.25,0,0.75,1]},{"time":0.7667,"x":0.843,"y":1,"curve":[0.25,0,0.75,1]},{"time":0.8667,"x":0.854,"y":1,"curve":[0.25,0,0.75,1]},{"time":1.1667,"x":0.85,"y":1}]},"youshou":{"rotate":[{"time":0,"angle":0,"curve":[0.25,0,0.75,1]},{"time":0.2,"angle":16.67,"curve":[0.25,0,0.75,1]},{"time":0.5333,"angle":-2.75,"curve":[0.25,0,0.75,1]},{"time":1.6667,"angle":0}],"translate":[{"time":0,"x":0,"y":0,"curve":[0.25,0,0.75,1]},{"time":0.5333,"x":2.9,"y":-1.43,"curve":[0.25,0,0.75,1]},{"time":0.8667,"x":-15.76,"y":-0.45,"curve":[0.25,0,0.75,1]},{"time":1.1333,"x":-14.43,"y":-1.1,"curve":[0.25,0,0.75,1]},{"time":1.3333,"x":-0.03,"y":-0.69,"curve":[0.25,0,0.75,1]},{"time":1.6667,"x":0,"y":0}],"scale":[{"time":0,"x":1,"y":1,"curve":[0.25,0,0.75,1]},{"time":0.7,"x":1.17,"y":1,"curve":[0.25,0,0.75,1]},{"time":1.0667,"x":1.13,"y":1,"curve":[0.25,0,0.75,1]},{"time":1.1333,"x":1,"y":1}]},"zuobi1":{"rotate":[{"time":0,"angle":0,"curve":[0.25,0,0.75,1]},{"time":0.5333,"angle":-1.64,"curve":[0.25,0,0.75,1]},{"time":1.6667,"angle":0}]},"zuoxia":{"rotate":[{"time":0,"angle":0,"curve":[0.25,0,0.75,1]},{"time":0.5333,"angle":0.87,"curve":[0.25,0,0.75,1]},{"time":1.6667,"angle":0}],"translate":[{"time":0,"x":0,"y":0,"curve":[0.25,0,0.75,1]},{"time":0.5333,"x":-0.49,"y":0.39,"curve":[0.25,0,0.75,1]},{"time":1.6667,"x":0,"y":0}]},"zuoshou":{"rotate":[{"time":0,"angle":0,"curve":"stepped"},{"time":1.6667,"angle":0}],"translate":[{"time":0,"x":0,"y":0,"curve":[0.25,0,0.75,1]},{"time":0.5333,"x":-0.89,"y":0.12,"curve":[0.25,0,0.75,1]},{"time":1.6667,"x":0,"y":0}]},"youxia2":{"rotate":[{"time":0,"angle":0,"curve":[0.25,0,0.75,1]},{"time":0.2,"angle":-27.02,"curve":[0.25,0,0.75,1]},{"time":0.5333,"angle":-64.21,"curve":[0.25,0,0.75,1]},{"time":0.8667,"angle":-80.08,"curve":[0.25,0,0.75,1]},{"time":1.4667,"angle":0}],"translate":[{"time":0,"x":0,"y":0,"curve":[0.25,0,0.75,1]},{"time":0.2,"x":-2.4,"y":1.24,"curve":[0.25,0,0.75,1]},{"time":0.5333,"x":-6.15,"y":3.3,"curve":[0.25,0,0.75,1]},{"time":0.8667,"x":-23.01,"y":-5.26,"curve":[0.25,0,0.75,1]},{"time":1.3,"x":-9.12,"y":-0.79,"curve":[0.25,0,0.75,1]},{"time":1.4667,"x":0,"y":0}]},"youshou4":{"rotate":[{"time":0,"angle":0,"curve":[0.25,0,0.75,1]},{"time":0.2,"angle":16.67,"curve":[0.25,0,0.75,1]},{"time":0.5333,"angle":-2.75,"curve":[0.25,0,0.75,1]},{"time":0.8667,"angle":4.09,"curve":[0.25,0,0.75,1]},{"time":1.4667,"angle":0,"curve":"stepped"},{"time":1.6667,"angle":0}],"translate":[{"time":0,"x":0,"y":0,"curve":[0.25,0,0.75,1]},{"time":0.2,"x":-0.26,"y":-0.11,"curve":[0.25,0,0.75,1]},{"time":0.5333,"x":-1.13,"y":0.43,"curve":[0.25,0,0.75,1]},{"time":0.8667,"x":-7.79,"y":-1.27,"curve":[0.25,0,0.75,1]},{"time":1.1333,"x":-8.02,"y":-0.42,"curve":[0.25,0,0.75,1]},{"time":1.4667,"x":0,"y":0,"curve":"stepped"},{"time":1.6667,"x":0,"y":0}]}},"deform":{"default":{"biyan2":{"biyan2":[{"time":0.3333,"offset":6,"vertices":[6.7393,-2.05674,11.79008,-4.5511,13.85795,-4.5332,13.06533,-5.2451,11.53319,-2.01524,7.64255,2.18123,5.47935,2.30352,4.52827,3.61131,3.26009,3.50633,0.92023,2.31104],"curve":[0.25,0,0.75,1]},{"time":0.4,"curve":"stepped"},{"time":0.4667,"curve":[0.25,0,0.75,1]},{"time":0.5333,"offset":6,"vertices":[6.7393,-2.05674,11.79008,-4.5511,13.85795,-4.5332,13.06533,-5.2451,11.53319,-2.01524,7.64255,2.18123,5.47935,2.30352,4.52827,3.61131,3.26009,3.50633,0.92023,2.31104]}]},"biyan3":{"biyan2":[{"time":0.3333,"offset":6,"vertices":[6.7393,-2.05674,11.79008,-4.5511,13.85795,-4.5332,13.06533,-5.2451,11.53319,-2.01524,7.64255,2.18123,5.47935,2.30352,4.52827,3.61131,3.26009,3.50633,0.92023,2.31104],"curve":[0.25,0,0.75,1]},{"time":0.4,"curve":"stepped"},{"time":0.4667,"curve":[0.25,0,0.75,1]},{"time":0.5333,"offset":6,"vertices":[6.7393,-2.05674,11.79008,-4.5511,13.85795,-4.5332,13.06533,-5.2451,11.53319,-2.01524,7.64255,2.18123,5.47935,2.30352,4.52827,3.61131,3.26009,3.50633,0.92023,2.31104]}]},"shenti":{"shenti":[{"time":0,"curve":[0.25,0,0.75,1]},{"time":0.2,"offset":40,"vertices":[0.01766,-0.73479,0,0,0.0106,-0.44086],"curve":[0.25,0,0.75,1]},{"time":0.5333,"offset":6,"vertices":[-0.00866,0.35989,-0.0522,2.17136,0.04253,-1.76949,0.12818,-5.33245,0.10454,-4.34874,0.1798,-7.47983,0,0,0,0,0,0,0,0,0,0,0,0,0,0,0,0,0,0,0,0,0,0,0.0602,-2.50427,0,0,0.02119,-0.88174,0,0,0.20078,-8.35256],"curve":[0.25,0,0.75,1]},{"time":1.1,"offset":40,"vertices":[0.01766,-0.73479,0,0,0.0106,-0.44086],"curve":[0.25,0,0.75,1]},{"time":1.3333}]},"youshang":{"youshang":[{"time":0,"curve":[0.25,0,0.75,1]},{"time":0.5333,"offset":10,"vertices":[-4.58651,-0.51073,-8.6705,-0.23688,-10.86419,-0.52899,-8.2607,-0.1679,-4.96089,1.37932,-4.6846,0.86099,-3.47316,1.42132],"curve":[0.25,0,0.75,1]},{"time":0.7333,"offset":6,"vertices":[-0.27621,-0.08995,-0.36445,0.03314,-5.76994,-0.43307,-11.88033,-0.57468,-12.94102,-1.57148,-7.81969,0.3834,-0.59201,1.32535,-5.14618,0.45103,-3.30579,1.10903,-0.55087,0.03069],"curve":[0.25,0,0.75,1]},{"time":1.1333,"offset":6,"vertices":[-0.97329,-0.31696,-1.28422,0.11679,-7.09385,-0.37272,-9.42989,-1.08519,-9.75591,-2.60511,-5.83128,-1.14801,-5.99419,-2.12697,-6.23098,-1.30217,-2.88337,0.3209,-1.94111,0.10813],"curve":[0.25,0,0.75,1]},{"time":1.2667,"offset":8,"vertices":[-3.10887,0.17979,-3.86274,-0.44318,-4.21903,-0.17849,-2.67705,0.03722,0,0,0,0,-1.96147,0.0707,-3.12545,1.22337],"curve":[0.25,0,0.625,0.5]},{"time":1.4,"curve":"stepped"},{"time":1.5667}]},"youshou4":{"youshou":[{"time":0,"curve":"stepped"},{"time":0.5333,"curve":[0.25,0,0.75,1]},{"time":0.8667,"vertices":[0.43132,0.89334,0,0,0,0,0,0,0,0,0,0,0,0,0,0,0,0,0,0,0,0,0,0,0,0,0.21183,0.7239,0.43132,0.89334,0.43132,0.89334,0.43132,0.89334,0,0,0,0,0.43132,0.89334,0,0,0.43132,0.89334],"curve":[0.25,0,0.75,1]},{"time":1.4667}]},"youxia":{"xiabi":[{"time":0,"curve":[0.25,0,0.75,1]},{"time":0.5333,"vertices":[-1.74828,1.76439,-1.91237,0.21611,0,0,0,0,0,0,0,0,0,0,0,0,11.20743,-0.81355,11.20743,-0.81355,11.20743,-0.81355,11.20743,-0.81355,11.20743,-0.81355,11.20743,-0.81355,0,0,0,0,0.01202,0.68413,-0.71613,0.78818,0.05602,0.59212],"curve":[0.25,0,0.75,1]},{"time":0.8667,"vertices":[-2.18337,4.0186,-1.15513,3.46584,6.62182,-1.97552,4.88834,-1.59183,2.25974,-0.18681,0.07562,-0.61275,-2.87269,0.3113,-5.97082,0.82735,-6.45916,0.04391,-8.78295,-0.48972,-12.13332,-1.47362,-12.34325,0.5729,-11.52581,-0.17534,-9.10037,-1.1021,-3.87849,-0.53941,-0.37309,-0.03042,0.00601,0.34207,-4.68453,1.26982,-1.38952,1.7498,1.51176,-2.28342,-1.68432,-1.52733,-9.00069,-1.48776,-7.75207,-1.25667],"curve":[0.25,0,0.75,1]},{"time":1.1667,"vertices":[0.2244,1.55568,-0.41105,-0.5491,2.2938,0.51525,3.72254,-0.53946,4.84923,-1.49068,2.83047,-1.388,0.95683,-0.49027,-1.3015,-0.03735,0.96977,-0.12408,-0.31276,-1.2905,1.36952,-2.70832,0.86073,-1.10609,1.51638,-0.09601,-1.88524,-0.51365,-3.71373,-0.33269,0.00014,0.00001,-0.00064,0.05402,-2.57092,0.36099,4.2202,0.53338,0.24045,-2.79153,-3.42244,-1.37159,1.50063,-2.64116,-0.55097,-2.69928],"curve":[0.25,0,0.625,0.5]},{"time":1.2333,"vertices":[2.50555,0.52519,3.05967,-2.42965,1.55816,-3.24713,0.06365,-2.14876,0.76423,-2.45841,0.10987,-1.59776,0.47837,-0.24512,5.42806,-0.49714,5.68468,-0.32287,8.61652,-1.89603,8.63812,-2.12368,7.39456,-1.02674,10.4088,-1.63998,10.35079,-1.21288,4.07743,-1.41346,0.00012,0.00001,-0.00337,0.23492,-1.50967,0.62776,5.10805,0.73763,-2.63949,-3.26293,3.70279,-0.80953,-0.47405,-2.09945,7.183,-1.68324],"curve":[0.375,0.5,0.75,1]},{"time":1.3,"vertices":[3.56015,-0.0152,0.2162,-0.39066,-1.90367,-5.71583,-3.59523,-3.75805,-3.32075,-3.42613,-2.61071,-1.80751,-0.00009,0.00003,6.19567,-0.59053,3.66216,-0.23819,10.20721,-0.38506,10.92154,-0.14389,10.24473,0.46003,10.05676,0.7533,1.04625,-1.13686,1.51406,-0.65658,0.00009,0.00001,-0.00609,0.41582,-0.44843,0.89452,5.9959,0.94188,-10.35592,-1.62891,-12.49147,0.35273,-7.23548,0.4089,5.8532,-0.63253],"curve":[0.25,0,0.75,1]},{"time":1.4667,"vertices":[0.06664,1.75316,0,0,1.28625,-1.62098,1.7829,-1.23042,0,0,0,0,0,0,0,0,0,0,7.50954,-1.61701,10.2828,-1.37287,11.05193,-0.68386,8.44041,0.74307,4.20772,0.47398,2.86887,0.45966,-0.1054,0.86437,-0.81984,1.35743,-0.3033,1.72059,2.19705,1.14649,0,0,5.00613,-0.07703,0,0,4.18712,-0.35624]}]},"youxia2":{"youxia":[{"time":0,"offset":4,"vertices":[3.30504,-0.5751,1.78791,-1.95537,2.50494,-0.03939,1.72955,2.60464,0.47128,0.93337],"curve":[0.25,0,0.75,1]},{"time":0.2,"offset":4,"vertices":[0.19014,-0.00358,0.09354,-3.15746,3.8504,-3.53154,3.06348,-1.09408,0.51591,-0.88411],"curve":[0.25,0,0.75,1]},{"time":0.5333,"offset":2,"vertices":[-1.87341,-0.59107,2.59518,-0.36405,2.90835,-1.86671,2.2706,-0.80517,3.17087,-0.70732,1.03381,-1.24279,0,0,-7.83157,-2.14352,-4.77427,-1.24673,-1.86701,-0.23325,-4.22748,-0.41993],"curve":[0.25,0,0.75,1]},{"time":0.8667,"vertices":[4.68772,-4.45756,9.28645,-4.61486,13.81794,-6.50706,14.88246,-3.80369,17.74067,-3.22657,14.49882,-1.67608,10.28421,-1.74983,4.01624,-0.99562,-10.17975,-3.06385,-10.74167,-2.2402,-9.50969,-0.09891,-8.01869,-2.32659,-0.95635,-2.64957,17.4934,-6.09457,12.55207,-3.29493],"curve":[0.242,0,0.667,0.67]},{"time":1.1667,"vertices":[-2.57516,-5.69749,-1.78631,-6.50573,1.98531,-10.23495,5.84752,-9.52461,9.44093,-7.74882,8.40455,-4.88814,5.35261,-4.91317,-0.85052,-4.19336,-5.69145,-1.41749,-5.64795,-1.06483,-5.43333,-0.7292,-5.44546,-1.75337,-2.80485,-3.36106,-1.36049,-7.4175,2.1443,-4.72333],"curve":[0.379,0.6,0.724,1]},{"time":1.2667,"vertices":[-2.33728,-6.10264,3.34555,-5.27662,-0.11301,-8.51516,1.78473,-9.89677,7.48893,-9.83287,6.10493,-5.45014,2.99295,-5.78179,-4.23067,-4.58615,-4.67624,-1.04509,-4.4958,-0.79897,-4.5113,-0.87177,-4.86343,-1.62371,-2.99957,-3.6951,-6.77411,-7.77367,-5.12241,-6.27905],"curve":[0.25,0,0.75,1]},{"time":1.3,"vertices":[-3.25369,-6.56766,-2.30488,-7.59013,0.04949,-7.86728,0.96167,-8.37423,2.82535,-8.20518,4.00966,-5.01866,0.37218,-5.63375,-5.89957,-5.39134,-3.79721,-0.71068,-3.79721,-0.71068,-3.79721,-0.71068,-4.30116,-1.67848,-3.21101,-3.96663,-5.25349,-7.6968,-8.45812,-7.22149],"curve":[0.25,0,0.75,1]},{"time":1.4,"vertices":[-1.19689,-2.41596,-1.19241,-1.91735,2.14561,-2.11886,-0.68021,-2.81152,1.59225,-2.58754,-0.19505,-1.11342,-1.12932,-2.11083,-1.04289,-2.56726,-1.39683,-0.26143,-1.39683,-0.26143,-1.39683,-0.26143,-1.58221,-0.61744,-1.18119,-1.45915,-2.23229,-3.4168,0.17642,-2.08539],"curve":[0.25,0,0.75,1]},{"time":1.4667,"offset":4,"vertices":[3.30504,-0.5751,1.78791,-1.95537,2.50494,-0.03939,1.72955,2.60464,0.47128,0.93337]}]}}},"drawOrder":[{"time":0.2,"offsets":[{"slot":"youxia","offset":9},{"slot":"youshou","offset":9},{"slot":"youshou4","offset":6},{"slot":"youxia2","offset":4}]},{"time":1.2667,"offsets":[{"slot":"youxia","offset":4},{"slot":"youshou","offset":4}]}]}}},[0]]],0,0,[0],[-1],[0]],[[[3,"prefabs_bandar_heguan"],[4,"prefabs_bandar_heguan",[-3],[[6,-2,[0,"b6u8l95QpOloWh2Ea+8Sgw"]]],[1,"c46/YsCPVOJYA4mWEpNYRx",null,null,null,-1,0]],[5,"props_croupier",1,[[7,-4,[0,"36Gi+by8tERL3rbNCrDUsY"],[5,142,174]],[8,"default","daiji",false,0,-5,[0,"93geW68nBGTbIYP5gzuVz8"],0]],[1,"a8ZS9s5CFK2J384rs6IcT3",null,null,null,1,0],[1,0,210,0]]],0,[0,1,1,0,0,1,0,-1,2,0,0,2,0,0,2,0,2,1,5],[0],[3],[1]]]]
